Metadata-Version: 2.1
Name: simple-socket-server
Version: 1.8
Summary: Simple TCP socket server with select
Home-page: https://github.com/webtoucher/simple-socket-server
Author: Alexey Kuznetsov
Author-email: mirakuru@webtoucher.ru
License: BSD-3-Clause
Classifier: Development Status :: 5 - Production/Stable
Classifier: Intended Audience :: Developers
Classifier: Topic :: Internet :: WWW/HTTP :: HTTP Servers
Classifier: License :: OSI Approved :: BSD License
Classifier: Programming Language :: Python :: 3
Classifier: Operating System :: Microsoft :: Windows
Classifier: Operating System :: POSIX
Classifier: Operating System :: Unix
Classifier: Operating System :: MacOS
License-File: LICENSE.md
